dbl_ingress/__init__.py
dbl_ingress/py.typed
dbl_ingress/reason_codes.py
dbl_ingress/admission/__init__.py
dbl_ingress/admission/errors.py
dbl_ingress/admission/json_types.py
dbl_ingress/admission/model.py
dbl_ingress/shaping/__init__.py
dbl_ingress/shaping/shape.py
dbl_ingress-0.1.1.dist-info/licenses/LICENSE
dbl_ingress-0.1.1.dist-info/METADATA
dbl_ingress-0.1.1.dist-info/WHEEL
dbl_ingress-0.1.1.dist-info/top_level.txt
dbl_ingress-0.1.1.dist-info/RECORD
